cheddar/__init__.py
cheddar/cheddar.py
cheddar/configuration.py
cheddar/environment.py
cheddar/errors.py
cheddar/messages.py
cheddar/payments.py
cheddar/requestor.py
cheddar/transactions.py
cheddar/utils.py
cheddar/version.py
cheddar/resources/__init__.py
cheddar/resources/currency.py
cheddar/resources/payment.py
cheddar/resources/service.py
cheddar/resources/transaction.py
cheddarpayments-0.7.1.dist-info/LICENSE
cheddarpayments-0.7.1.dist-info/METADATA
cheddarpayments-0.7.1.dist-info/WHEEL
cheddarpayments-0.7.1.dist-info/top_level.txt
cheddarpayments-0.7.1.dist-info/RECORD
