Metadata-Version: 2.1
Name: cheddarpayments
Version: 0.7.1
Summary: Cheddar Python Bindings
Home-page: https://www.backbone.sk/en/
Author: Palo Sopko
Author-email: pavol.sopko@backbone.sk
License: MIT
Project-URL: Bug Tracker, https://github.com/backbonesk/cheddar-python/issues
Project-URL: Source Code, https://github.com/backbonesk/cheddar-python
Keywords: cheddar,api,payments,money,cardpay,comfortpay,tatrapay,trustpay,sporopay,eplatby,gpwebpay,iterminal
Platform: UNKNOWN
Classifier: Development Status :: 5 - Production/Stable
Classifier: Intended Audience :: Developers
Classifier: License :: OSI Approved :: MIT License
Classifier: Operating System :: OS Independent
Classifier: Programming Language :: Python
Classifier: Programming Language :: Python :: 2
Classifier: Programming Language :: Python :: 2.7
Classifier: Programming Language :: Python :: 3
Classifier: Programming Language :: Python :: 3.4
Classifier: Programming Language :: Python :: 3.5
Classifier: Programming Language :: Python :: 3.6
Classifier: Programming Language :: Python :: 3.7
Classifier: Programming Language :: Python :: 3.8
Classifier: Programming Language :: Python :: Implementation :: PyPy
Classifier: Topic :: Software Development :: Libraries :: Python Modules
Requires-Python: >=2.7, !=3.0.*, !=3.1.*, !=3.2.*, !=3.3.*
License-File: LICENSE
Requires-Dist: requests (>=2.21.0)
Requires-Dist: six (>=1.3.0)
